ufmt/__init__.py
ufmt/__main__.py
ufmt/__version__.py
ufmt/cli.py
ufmt/config.py
ufmt/core.py
ufmt/lsp.py
ufmt/py.typed
ufmt/types.py
ufmt/util.py
ufmt/tests/__init__.py
ufmt/tests/__main__.py
ufmt/tests/benchmark.py
ufmt/tests/cli.py
ufmt/tests/config.py
ufmt/tests/core.py
ufmt/tests/util.py
ufmt-2.7.3.dist-info/entry_points.txt
ufmt-2.7.3.dist-info/LICENSE
ufmt-2.7.3.dist-info/WHEEL
ufmt-2.7.3.dist-info/METADATA
ufmt-2.7.3.dist-info/RECORD
