Metadata-Version: 2.1
Name: ufmt
Version: 2.7.3
Summary: Safe, atomic formatting with black and µsort
Author-email: Amethyst Reese <amy@n7.gg>
Requires-Python: >= 3.8
Classifier: Development Status :: 5 - Production/Stable
Classifier: Intended Audience :: Developers
Classifier: License :: OSI Approved :: MIT License
Classifier: Topic :: Utilities
Classifier: Typing :: Typed
Requires-Dist: black>=20.8b0
Requires-Dist: click>=8.0
Requires-Dist: libcst>=0.4.0
Requires-Dist: moreorless>=0.4.0
Requires-Dist: tomlkit>=0.7.2
Requires-Dist: trailrunner>=1.2.1
Requires-Dist: typing-extensions>=4.0
Requires-Dist: usort>=1.0
Requires-Dist: attribution==1.8.0 ; extra == "dev"
Requires-Dist: black==24.8.0 ; extra == "dev"
Requires-Dist: build>=1.2 ; extra == "dev"
Requires-Dist: coverage>=7 ; extra == "dev"
Requires-Dist: flake8==7.1.1 ; extra == "dev"
Requires-Dist: mypy==1.11.2 ; extra == "dev"
Requires-Dist: pygls==1.3.1 ; extra == "dev"
Requires-Dist: ruff-api==0.0.8 ; extra == "dev"
Requires-Dist: usort==1.0.8.post1 ; extra == "dev"
Requires-Dist: sphinx==8.0.2 ; extra == "docs"
Requires-Dist: sphinx-mdinclude==0.6.2 ; extra == "docs"
Requires-Dist: pygls >= 1.3 ; extra == "lsp"
Requires-Dist: ruff-api>=0.0.8 ; extra == "ruff"
Project-URL: Changelog, https://ufmt.omnilib.dev/en/latest/changelog.html
Project-URL: Documentation, https://ufmt.omnilib.dev
Project-URL: Github, https://github.com/omnilib/ufmt
Provides-Extra: dev
Provides-Extra: docs
Provides-Extra: lsp
Provides-Extra: ruff
